[
  {
    "txid": "TX001",
    "status": "Completed",
    "network": "TRC20",
    "asset": "USDT",
    "amount": "250",
    "confirmations": "20/20",
    "risk": "Low",
    "wallet": "Healthy",
    "note": "Deposit confirmed successfully."
  },
  {
    "txid": "TX002",
    "status": "Pending",
    "network": "ERC20",
    "asset": "USDT",
    "amount": "500",
    "confirmations": "8/20",
    "risk": "Low",
    "wallet": "Healthy",
    "note": "Waiting for blockchain confirmations."
  },
  {
    "txid": "TX003",
    "status": "Wrong Network",
    "network": "BEP20",
    "asset": "USDT",
    "amount": "120",
    "confirmations": "-",
    "risk": "Medium",
    "wallet": "Manual Review",
    "note": "User selected an unsupported network."
  },
  {
    "txid": "TX004",
    "status": "Missing Memo",
    "network": "XRP",
    "asset": "XRP",
    "amount": "950",
    "confirmations": "Validated",
    "risk": "Medium",
    "wallet": "Manual Review",
    "note": "Destination Tag was not included."
  },
  {
    "txid": "TX005",
    "status": "High Risk",
    "network": "Ethereum",
    "asset": "ETH",
    "amount": "12",
    "confirmations": "25/25",
    "risk": "High",
    "wallet": "Frozen",
    "note": "Transaction flagged by risk engine."
  }
]
